[
  {
    "name": "First Product",
    "price": 60,
    "ordernumber": "23E0125",
    "purchasedon": "01 March 2021",
    "Image": "https://themes.programmingkit.xyz/rafcart/assets/images/product8.jpg",
    "quantity": 2,
    "total": 120,
    "status": "Cancelled"
  },
  {
    "name": "Second Product",
    "price": 50,
    "ordernumber": "23E0125",
    "purchasedon": "01 March 2021",
    "Image": "https://themes.programmingkit.xyz/rafcart/assets/images/product9.jpg",
    "quantity": 3,
    "total": 150,
    "status": "Delivered"
  }
]
